snapmesh/__init__.py
snapmesh-0.1.0.dist-info/licenses/LICENSE
snapmesh-0.1.0.dist-info/METADATA
snapmesh-0.1.0.dist-info/WHEEL
snapmesh-0.1.0.dist-info/top_level.txt
snapmesh-0.1.0.dist-info/RECORD
