Metadata-Version: 2.4
Name: snapmesh
Version: 0.1.0
Summary: A geometry-aware adaptive meshing tool
Author-email: Chris Burnside <christopher.g.burnside@gmail.com>
License: MIT License
Project-URL: Homepage, https://github.com/cgburnsi/snapmesh
Project-URL: Bug Tracker, https://github.com/cgburnsi/snapmesh/issues
Classifier: Programming Language :: Python :: 3
Classifier: License :: OSI Approved :: MIT License
Classifier: Operating System :: OS Independent
Classifier: Topic :: Scientific/Engineering :: Physics
Classifier: Topic :: Scientific/Engineering :: Chemistry
Requires-Python: >=3.8
License-File: LICENSE
Requires-Dist: numpy
Requires-Dist: matplotlib
Dynamic: license-file
